pixels-0.0.1a0.data/purelib/dearpygui/__init__.py
pixels-0.0.1a0.data/purelib/dearpygui/dearpygui.py
pixels-0.0.1a0.data/purelib/dearpygui/demo.py
pixels-0.0.1a0.data/purelib/dearpygui/logger.py
pixels-0.0.1a0.data/purelib/dearpygui/themes.py
pixels-0.0.1a0.dist-info/LICENSE
pixels-0.0.1a0.dist-info/METADATA
pixels-0.0.1a0.dist-info/WHEEL
pixels-0.0.1a0.dist-info/top_level.txt
pixels-0.0.1a0.dist-info/RECORD
